<?xml version="1.0" encoding="UTF-8"?><magicdraw><literalboolean classType="LiteralBoolean" humanType="Literal Boolean" icon="MDMIExampleModel_files/icon_literalboolean_22543832.png" id="_19_0_3_62501eb_1581544907590_867194_7002"><documentation humanName="Documentation"/><name humanName="Name"/><owner classType="Slot" humanName="Owner" humanType="Slot" icon="MDMIExampleModel_files/icon_slot_34298277.png" mode="e" refid="_19_0_3_62501eb_1581544907588_708876_6981"/><owningSlot classType="Slot" humanName="Owning Slot" humanType="Slot" icon="MDMIExampleModel_files/icon_slot_34298277.png" refid="_19_0_3_62501eb_1581544907588_708876_6981"/><qualifiedName humanName="Qualified Name"/><text humanName="Text" mode="standard">false</text><TO_DO humanName="To Do"/><TYPE_MODIFIER humanName="Type Modifier"/><value humanName="Value" mode="s,e">false</value><visibility humanName="Visibility">public</visibility></literalboolean></magicdraw>